{"site_symmetries": ["1", "2"], "pointgroup": "mm2", "radii": [0.045, 0.05, 0.055, 0.06, 0.065, 0.07, 0.075, 0.08, 0.085, 0.09, 0.095, 0.1, 0.105, 0.11, 0.115, 0.12, 0.125, 0.13, 0.135, 0.14, 0.145, 0.15, 0.155, 0.16, 0.165, 0.17, 0.175], "CN": [1, 4], "IBZ_sphericity": 0.5252229898596701, "connection_radius": 0.1348392458844348, "min_connection_radius": 0.1333128344563427, "has_gaps_at": [], "common_name": "Germanium Samaride", "num_jobs": 44, "code": 4332826, "structure_url": "https://doi.org/10.1021/ic060913f", "sg_number": 43, "wyckoff_positions": ["a", "b"], "has_gap": false, "code_source": "COD", "_id(old)": "eaec45745a3159f50aac039d6d07f3b1", "omega_stars": [], "_structure(old)": "oF16-Ge5Sm3", "fix_name": false, "fill_fraction": [0.025217, NaN, 0.044238, 0.057004, 0.072426, 0.090277, 0.111204, 0.134797, 0.161897, 0.192162, NaN, 0.263443, 0.304991, 0.350431, 0.400497, 0.454345, 0.510624, 0.570494, 0.63344, NaN, 0.756759, 0.810788, NaN, 0.895224, 0.926101, NaN, 0.971416], "international": "dd2", "connection_phi": 0.63344, "min_connection_phi": 0.63344, "void_connection_phi": 0.302709, "kp_labels": ["GAMMA", "Y", "T", "Z", "GAMMA", "SIGMA_0", "U_0", "T", "Y", "C_0", "A_0", "Z", "GAMMA", "L"], "kpoints": [[0.0, 0.0, 0.0], [0.5, 0.0, 0.5], [1.0, 0.5, 0.5], [0.5, 0.5, 0.0], [0.0, 0.0, 0.0], [0.0, 0.3219138932316261, 0.3219138932316261], [1.0, 0.6780861067683739, 0.6780861067683739], [1.0, 0.5, 0.5], [0.5, 0.0, 0.5], [0.5, 0.2663055494057103, 0.7663055494057103], [0.5, 0.7336944505942897, 0.23369445059428973], [0.5, 0.5, 0.0], [0.0, 0.0, 0.0], [0.5, 0.5, 0.5]], "kpoints_from": "seekpath, 2024", "pdos_stored": false, "outputs_still_to_do": 5}