{"IBZ_sphericity": 0.4141786338574704, "common_name": "Calcium Nitrogen Tin", "connection_radius": 0.14870392044412553, "structure_url": "https://doi.org/10.1016/0022-5088(91)90020-5", "sg_number": 83, "min_connection_radius": 0.1132508291601117, "pointgroup": "4/m", "fill_fraction": [0.016487, 0.03065, 0.052778, 0.084131, 0.125486, 0.178789, 0.245229, 0.326121, 0.422268, 0.528926, 0.644497, 0.767837, 0.875364, 0.942993, 0.976582, 0.992507], "omega_stars": [], "fix_name": false, "code": 1528162, "num_jobs": 16, "has_gap": false, "radii": [0.04, 0.05, 0.06, 0.07, 0.08, 0.09, 0.1, 0.11, 0.12, 0.13, 0.14, 0.15, 0.16, 0.17, 0.18, 0.19], "site_symmetries": ["4/m", "4/m", "2/m", "m", "m"], "code_source": "COD", "wyckoff_positions": ["a", "c", "f", "j", "k"], "CN": [2, 3, 4, 8], "connection_phi": 0.767837, "min_connection_phi": 0.326121, "void_connection_phi": 0.355503, "kp_labels": ["GAMMA", "X", "M", "GAMMA", "Z", "R", "A", "Z", "X", "R", "M", "A"], "kpoints": [[0.0, 0.0, 0.0], [0.0, 0.5, 0.0], [0.5, 0.5, 0.0], [0.0, 0.0, 0.0], [0.0, 0.0, 0.5], [0.0, 0.5, 0.5], [0.5, 0.5, 0.5], [0.0, 0.0, 0.5], [0.0, 0.5, 0.0], [0.0, 0.5, 0.5], [0.5, 0.5, 0.0], [0.5, 0.5, 0.5]], "kpoints_from": "seekpath, 2024", "pdos_stored": false}