{"IBZ_sphericity": 0.4455506336634301, "common_name": "Eriochalcite", "connection_radius": 0.14045835276058755, "structure_url": "https://doi.org/10.1524/zkri.1936.94.1.231", "name_checked": true, "sg_number": 53, "min_connection_radius": 0.12499999999999999, "pointgroup": "mmm", "fill_fraction": [0.022146, 0.033777, NaN, 0.07177, 0.098423, NaN, 0.169985, 0.215697, NaN, 0.325742, NaN, NaN, NaN, 0.606371, 0.684627, 0.759518, NaN, 0.896318, 0.945673, NaN], "omega_stars": [], "fix_name": false, "code": 1010979, "num_jobs": 23, "has_gap": false, "radii": [0.06, 0.07, 0.08, 0.09, 0.1, 0.11, 0.12, 0.13, 0.14, 0.15, 0.16, 0.17, 0.18, 0.19, 0.2, 0.21, 0.22, 0.23, 0.24, 0.25], "site_symmetries": ["m", "2/m", "2"], "code_source": "COD", "wyckoff_positions": ["d", "h", "f"], "CN": [1, 2], "connection_phi": 0.267938, "min_connection_phi": 0.169985, "void_connection_phi": 0.168887, "kp_labels": ["GAMMA", "X", "S", "Y", "GAMMA", "Z", "U", "R", "T", "Z", "X", "U", "Y", "T", "S", "R"], "kpoints": [[0.0, 0.0, 0.0], [0.5, 0.0, 0.0], [0.5, 0.5, 0.0], [0.0, 0.5, 0.0], [0.0, 0.0, 0.0], [0.0, 0.0, 0.5], [0.5, 0.0, 0.5], [0.5, 0.5, 0.5], [0.0, 0.5, 0.5], [0.0, 0.0, 0.5], [0.5, 0.0, 0.0], [0.5, 0.0, 0.5], [0.0, 0.5, 0.0], [0.0, 0.5, 0.5], [0.5, 0.5, 0.0], [0.5, 0.5, 0.5]], "kpoints_from": "seekpath, 2024", "pdos_stored": false, "outputs_still_to_do": 8}