{"IBZ_sphericity": 0.5112947734911608, "common_name": "Tetrachlorophosphonium Hexafluoroantimonate", "connection_radius": 0.11257681616514786, "structure_url": "https://doi.org/10.1107/S0108270192001173", "sg_number": 85, "min_connection_radius": 0.10880869680315079, "pointgroup": "4/m", "fill_fraction": [0.028543, 0.045302, 0.06757, 0.096299, 0.131885, NaN, 0.226271, 0.282374, NaN, 0.410647, NaN, NaN, NaN, 0.718016, 0.795328, 0.860276, NaN, 0.947276, 0.972602], "omega_stars": [], "fix_name": false, "code": 2000605, "num_jobs": 23, "has_gap": false, "radii": [0.06, 0.07, 0.08, 0.09, 0.1, 0.11, 0.12, 0.13, 0.14, 0.15, 0.16, 0.17, 0.18, 0.19, 0.2, 0.21, 0.22, 0.23, 0.24], "site_symmetries": ["-4", "4", "1"], "code_source": "COD", "wyckoff_positions": ["a", "c", "g"], "CN": [1, 4], "connection_phi": 0.175522, "min_connection_phi": 0.175522, "void_connection_phi": 0.281984, "kp_labels": ["GAMMA", "X", "M", "GAMMA", "Z", "R", "A", "Z", "X", "R", "M", "A"], "kpoints": [[0.0, 0.0, 0.0], [0.0, 0.5, 0.0], [0.5, 0.5, 0.0], [0.0, 0.0, 0.0], [0.0, 0.0, 0.5], [0.0, 0.5, 0.5], [0.5, 0.5, 0.5], [0.0, 0.0, 0.5], [0.0, 0.5, 0.0], [0.0, 0.5, 0.5], [0.5, 0.5, 0.0], [0.5, 0.5, 0.5]], "kpoints_from": "seekpath, 2024", "pdos_stored": false, "outputs_still_to_do": 6}