{"std_lattice": [[1.0, 0.0, 0.0], [0.0, 1.0, 0.0], [0.0, 0.0, 1.51378982]], "site_point_groups": {"c": {"name": "1c", "site_symmetry": ["2", "1", "-4"]}, "g": {"name": "2g", "site_symmetry": ["2", "1"]}, "b": {"name": "1b", "site_symmetry": ["2", "1", "-4"]}, "h": {"name": "4h", "site_symmetry": ["1"]}}, "equivalent_atoms": [0, 1, 2, 2, 4, 4, 4, 4, 8, 8, 8, 8], "global_point_groups": ["-4", "1", "2"], "wyckoffs": ["b", "c", "g", "g", "h", "h", "h", "h", "h", "h", "h", "h"], "international": "P-4", "std_positions": [[0.0, 0.0, 0.5], [0.5, 0.5, 0.0], [0.0, 0.5, 0.248], [0.5, 0.0, 0.752], [0.3599, 0.2566, 0.8703], [0.6401, 0.7434, 0.8703], [0.7434, 0.3599, 0.1297], [0.2566, 0.6401, 0.1297], [0.1367, 0.2552, 0.3798], [0.8633, 0.7448, 0.3798], [0.7448, 0.1367, 0.6202], [0.2552, 0.8633, 0.6202]], "number": 81}