{"IBZ_sphericity": 0.5134548019029439, "_structure(old)": "tP16-Cu4LaP3", "connection_radius": 0.26394271107827, "omega_stars": [], "common_name": "Distorted Phosphorus And Copper Square- planar Layers In Lacu1+xp2", "has_gap": false, "CN": [1, 4], "code_source": "COD", "site_symmetries": ["4mm", "mm2", "m"], "has_gaps_at": [], "fill_fraction": [0.027089, 0.038431, 0.052823, NaN, 0.091231, 0.115957, NaN, 0.178129, 0.216115, NaN, NaN, 0.361387, 0.421717, 0.488059, NaN, 0.623259, 0.688341, NaN, 0.803073, NaN, 0.900582, 0.934557, 0.956559, 0.970828, NaN, NaN], "fix_name": false, "international": "4/nmm", "pointgroup": "4/mmm", "structure_url": "https://doi.org/10.1021/ic502234w", "num_jobs": 41, "sg_number": 129, "wyckoff_positions": ["j", "c", "f"], "code": 4341413, "min_connection_radius": 0.19487401233794, "_id(old)": "5bf7e7f001bc15ea435cb002b49ec6c8", "radii": [0.08, 0.09, 0.1, 0.11, 0.12, 0.13, 0.14, 0.15, 0.16, 0.17, 0.18, 0.19, 0.2, 0.21, 0.22, 0.23, 0.24, 0.25, 0.26, 0.27, 0.28, 0.29, 0.3, 0.31, 0.32, 0.33], "connection_phi": 0.688341, "min_connection_phi": 0.259237, "void_connection_phi": 0.252609, "kp_labels": ["GAMMA", "X", "M", "GAMMA", "Z", "R", "A", "Z", "X", "R", "M", "A"], "kpoints": [[0.0, 0.0, 0.0], [0.0, 0.5, 0.0], [0.5, 0.5, 0.0], [0.0, 0.0, 0.0], [0.0, 0.0, 0.5], [0.0, 0.5, 0.5], [0.5, 0.5, 0.5], [0.0, 0.0, 0.5], [0.0, 0.5, 0.0], [0.0, 0.5, 0.5], [0.5, 0.5, 0.0], [0.5, 0.5, 0.5]], "kpoints_from": "seekpath, 2024", "pdos_stored": false, "outputs_still_to_do": 9}