{"IBZ_sphericity": 0.4244129571397849, "common_name": "Silverbismutate (iii)", "connection_radius": 0.07572842284440472, "structure_url": "https://doi.org/10.1002/zaac.19966220325", "sg_number": 52, "min_connection_radius": 0.07354786248647086, "pointgroup": "mmm", "fill_fraction": [0.0225528, NaN, 0.0472492, NaN, 0.0936624, NaN, 0.162123, NaN, 0.257952, NaN, 0.382221, NaN, 0.519555, NaN, 0.662906, NaN, 0.801443, NaN, 0.905834, NaN, 0.959629], "omega_stars": [], "fix_name": false, "code": 1509869, "num_jobs": 15, "has_gap": false, "radii": [0.03, 0.035, 0.04, 0.045, 0.05, 0.055, 0.06, 0.065, 0.07, 0.075, 0.08, 0.085, 0.09, 0.095, 0.1, 0.105, 0.11, 0.115, 0.12, 0.125, 0.13], "site_symmetries": ["2", "1", "2"], "code_source": "COD", "wyckoff_positions": ["d", "e", "c"], "CN": [1, 2], "connection_phi": 0.382221, "min_connection_phi": 0.257952, "void_connection_phi": 0.337094, "kp_labels": ["GAMMA", "X", "S", "Y", "GAMMA", "Z", "U", "R", "T", "Z", "X", "U", "Y", "T", "S", "R"], "kpoints": [[0.0, 0.0, 0.0], [0.5, 0.0, 0.0], [0.5, 0.5, 0.0], [0.0, 0.5, 0.0], [0.0, 0.0, 0.0], [0.0, 0.0, 0.5], [0.5, 0.0, 0.5], [0.5, 0.5, 0.5], [0.0, 0.5, 0.5], [0.0, 0.0, 0.5], [0.5, 0.0, 0.0], [0.5, 0.0, 0.5], [0.0, 0.5, 0.0], [0.0, 0.5, 0.5], [0.5, 0.5, 0.0], [0.5, 0.5, 0.5]], "kpoints_from": "seekpath, 2024", "pdos_stored": false, "outputs_still_to_do": 10}