{"structure_url": "https://doi.org/10.1107/S1600536810036445", "void_clusters": [NaN, NaN, NaN, NaN, NaN, 1, 1, 1, 1, 1, 1, 1, 1, 1, 1, 1, 1, 1, 1, 1, 1, 1, 1, 1, 1, 1, 1, 1, 1, 1, 1, 1, 1, 1, 1, 1, 5, 1, 5, 20, 32, 16, 8, 8, 8, 0.0, 0.0, 0.0, 0.0, 0.0, 0.0, 0.0, 0.0, 0.0, 0.0, 0.0, 0.0, 0.0, 0.0, 0.0, 0.0, 0.0, 0.0, 0.0, 0.0, 0.0, 0.0, 0.0, 0.0, 0.0, 0.0, 0.0, 0.0, 0.0, 0.0, 0.0, 0.0, 0.0, 0.0, 0.0, 0.0, 0.0, 0.0, 0.0, 0.0, 0.0, 0.0, 0.0, 0.0, 0.0, 0.0, 0.0, 0.0, 0.0, 0.0, 0.0, 0.0, 0.0, 0.0, 0.0, 0.0], "_structure(old)": "oP60-Al2Ca2O9Sn2_r", "num_jobs": 101, "fix_name": false, "has_gap": false, "min_connection_radius": 0.115074522497483, "site_symmetries": ["2", "1"], "has_gaps_at": [], "pointgroup": "mmm", "wyckoff_positions": ["c", "d"], "_id(old)": "1e845c207f722ef1208d661efcd32f6b", "code": 2227193, "sg_number": 60, "code_source": "COD", "omega_stars": [], "international": "bcn", "IBZ_sphericity": 0.4098692603270147, "fill_fraction": [0.977384, 0.969053, 0.958814, 0.946375, 0.931828, 0.914899, 0.895339, 0.873013, 0.847616, 0.819157, 0.78721, 0.752104, 0.713934, 0.67304, 0.629349, 0.583474, 0.536364, 0.48786, 0.438586, 0.389416, 0.341702, 0.29533, 0.25119, 0.20963, 0.170721, 0.136132, 0.104022, 0.077114, 0.052981, 0.03518, 0.020983], "connection_radius": 0.155, "radii": [0.045, 0.05, 0.055, 0.06, 0.065, 0.07, 0.075, 0.08, 0.085, 0.09, 0.095, 0.1, 0.105, 0.11, 0.115, 0.12, 0.125, 0.13, 0.135, 0.14, 0.145, 0.15, 0.155, 0.16, 0.165, 0.17, 0.175, 0.18, 0.185, 0.19, 0.195], "CN": [1, 2], "common_name": "Inverse Calcium Tin Aluminum Oxide", "connection_radii": [[0.2, 0.25, 0.3, 0.35, 0.4, 0.45, 0.5, 0.55, 0.6, 0.65, 0.7, 0.75, 0.8, 0.85, 0.9, 0.95], [0.24, 0.215, 0.215, 0.215, 0.2, 0.19, 0.19, 0.19, 0.19, 0.19, 0.19, 0.19, 0.175, 0.17, 0.17, 0.155]], "connection_phi": 0.25119, "void_connection_phi": 0.51214, "kp_labels": ["GAMMA", "X", "S", "Y", "GAMMA", "Z", "U", "R", "T", "Z", "X", "U", "Y", "T", "S", "R"], "kpoints": [[0.0, 0.0, 0.0], [0.5, 0.0, 0.0], [0.5, 0.5, 0.0], [0.0, 0.5, 0.0], [0.0, 0.0, 0.0], [0.0, 0.0, 0.5], [0.5, 0.0, 0.5], [0.5, 0.5, 0.5], [0.0, 0.5, 0.5], [0.0, 0.0, 0.5], [0.5, 0.0, 0.0], [0.5, 0.0, 0.5], [0.0, 0.5, 0.0], [0.0, 0.5, 0.5], [0.5, 0.5, 0.0], [0.5, 0.5, 0.5]], "kpoints_from": "seekpath, 2024", "pdos_stored": true}